setup.py
voyager/__init__.py
voyager/http_client.py
voyager/table.py
voyager/user.py
voyager/vclient.py
voyager/voyager_version.py
voyager_python.egg-info/PKG-INFO
voyager_python.egg-info/SOURCES.txt
voyager_python.egg-info/dependency_links.txt
voyager_python.egg-info/requires.txt
voyager_python.egg-info/top_level.txt