Metadata-Version: 1.0
Name: voyager-python
Version: 1.0
Summary: Python wrapper around DataNitro Voyager API
Home-page: https://github.com/datanitro/voyager-python
Author: DataNitro
Author-email: support@datanitro.com
License: MIT License
Platform: UNKNOWN
